{
  "db_name": "PostgreSQL",
  "query": "INSERT INTO banlist (membership_id, banned_until, reason)\n                        VALUES ($1, NOW() + ($2 || ' seconds')::interval, $3)\n                        ON CONFLICT (membership_id) DO UPDATE \n                        SET banned_until = NOW() + ($2 || ' seconds')::interval, reason = $3",
  "describe": {
    "columns": [],
    "parameters": {
      "Left": [
        "Text",
        "Text",
        "Text"
      ]
    },
    "nullable": []
  },
  "hash": "afea8c7bce71305ef3c6a9293f08ed59f2d795d53721203c925ac0189a974a98"
}
